micoda-0.1.0.dist-info/METADATA
micoda-0.1.0.dist-info/WHEEL
micoda/__init__.py
micoda/__init__.pyi
micoda/py.typed
micoda/micoda.cpython-38-x86_64-linux-gnu.so
micoda-0.1.0.dist-info/RECORD
